{
  "links": [
    {
      "text": "Baltimore City Public School System, Maryland",
      "href": "https://ballotpedia.org/Baltimore_City_Public_School_System,_Maryland"
    },
    {
      "text": "Allegany County Public Schools, Maryland",
      "href": "https://ballotpedia.org/Allegany_County_Public_Schools,_Maryland"
    },
    {
      "text": "Worcester County Public Schools, Maryland",
      "href": "https://ballotpedia.org/Worcester_County_Public_Schools,_Maryland"
    },
    {
      "text": "Baltimore County Public Schools, Maryland",
      "href": "https://ballotpedia.org/Baltimore_County_Public_Schools,_Maryland"
    },
    {
      "text": "Anne Arundel County Public Schools, Maryland",
      "href": "https://ballotpedia.org/Anne_Arundel_County_Public_Schools,_Maryland"
    },
    {
      "text": "Caroline County Public Schools, Maryland",
      "href": "https://ballotpedia.org/Caroline_County_Public_Schools,_Maryland"
    },
    {
      "text": "Carroll County Public Schools, Maryland",
      "href": "https://ballotpedia.org/Carroll_County_Public_Schools,_Maryland"
    },
    {
      "text": "Cecil County Public Schools, Maryland",
      "href": "https://ballotpedia.org/Cecil_County_Public_Schools,_Maryland"
    },
    {
      "text": "Charles County Public Schools, Maryland",
      "href": "https://ballotpedia.org/Charles_County_Public_Schools,_Maryland"
    },
    {
      "text": "Wicomico County Public Schools, Maryland",
      "href": "https://ballotpedia.org/Wicomico_County_Public_Schools,_Maryland"
    },
    {
      "text": "Garrett County Public Schools, Maryland",
      "href": "https://ballotpedia.org/Garrett_County_Public_Schools,_Maryland"
    },
    {
      "text": "Prince George's County Public Schools, Maryland",
      "href": "https://ballotpedia.org/Prince_George%27s_County_Public_Schools,_Maryland"
    },
    {
      "text": "Harford County Public Schools, Maryland",
      "href": "https://ballotpedia.org/Harford_County_Public_Schools,_Maryland"
    },
    {
      "text": "Queen Anne's County Public Schools, Maryland",
      "href": "https://ballotpedia.org/Queen_Anne%27s_County_Public_Schools,_Maryland"
    },
    {
      "text": "Kent County Public Schools, Maryland",
      "href": "https://ballotpedia.org/Kent_County_Public_Schools,_Maryland"
    },
    {
      "text": "Somerset County Public Schools, Maryland",
      "href": "https://ballotpedia.org/Somerset_County_Public_Schools,_Maryland"
    },
    {
      "text": "Montgomery County Public Schools, Maryland",
      "href": "https://ballotpedia.org/Montgomery_County_Public_Schools,_Maryland"
    },
    {
      "text": "St. Mary's County Public Schools, Maryland",
      "href": "https://ballotpedia.org/St._Mary%27s_County_Public_Schools,_Maryland"
    },
    {
      "text": "Talbot County Public Schools, Maryland",
      "href": "https://ballotpedia.org/Talbot_County_Public_Schools,_Maryland"
    },
    {
      "text": "Washington County Public Schools, Maryland",
      "href": "https://ballotpedia.org/Washington_County_Public_Schools,_Maryland"
    },
    {
      "text": "Dorchester County Public Schools, Maryland",
      "href": "https://ballotpedia.org/Dorchester_County_Public_Schools,_Maryland"
    },
    {
      "text": "Calvert County Public Schools, Maryland",
      "href": "https://ballotpedia.org/Calvert_County_Public_Schools,_Maryland"
    },
    {
      "text": "Howard County Public Schools, Maryland",
      "href": "https://ballotpedia.org/Howard_County_Public_Schools,_Maryland"
    },
    {
      "text": "Frederick County Public Schools, Maryland",
      "href": "https://ballotpedia.org/Frederick_County_Public_Schools,_Maryland"
    }
  ],
  "count": 24
}